sphedron/__init__.py
sphedron/extra.py
sphedron/helpers.py
sphedron/mesh/__init__.py
sphedron/mesh/base.py
sphedron/mesh/nested.py
sphedron/mesh/refinables.py
sphedron/refine.py
sphedron/transfer.py
sphedron/transform.py
sphedron-0.1.1.dist-info/LICENSE.txt
sphedron-0.1.1.dist-info/METADATA
sphedron-0.1.1.dist-info/WHEEL
sphedron-0.1.1.dist-info/RECORD
