Metadata-Version: 2.3
Name: sphedron
Version: 0.1.1
Summary: Polyhedral meshes on the unit sphere
Author: Ayoub Ghriss
Author-email: dev@ayghri.com
Requires-Python: >=3.10
Classifier: Programming Language :: Python :: 3
Classifier: Programming Language :: Python :: 3.10
Classifier: Programming Language :: Python :: 3.11
Classifier: Programming Language :: Python :: 3.12
Classifier: Programming Language :: Python :: 3.13
Provides-Extra: plot
Requires-Dist: cartopy (>=0.23.0,<0.24.0) ; extra == "plot"
Requires-Dist: numpy (>=2.0.1,<3.0.0)
Requires-Dist: scipy (>=1.14.0,<2.0.0)
Requires-Dist: shapely (>=2.0.5,<3.0.0) ; extra == "plot"
Requires-Dist: trimesh (>=4.5.3,<5.0.0)
Project-URL: Homepage, https://github.com/ayghri/sphedron
